{
  "timestamp": "2025-08-27T15:01:23.251320+00:00",
  "forecasts": [
    {
      "group": "Portsalon_4Sep",
      "time": "2025-09-04T12:00:00+00:00",
      "Temperature": 13.0,
      "WindDirection": 230.8,
      "WindSpeed": 13
    },
    {
      "group": "Portsalon_4Sep",
      "time": "2025-09-04T18:00:00+00:00",
      "Temperature": 12.2,
      "WindDirection": 286.6,
      "WindSpeed": 13
    },
    {
      "group": "OldTomMorris_5Sep",
      "time": "2025-09-05T12:00:00+00:00",
      "Temperature": 15.2,
      "WindDirection": 291.9,
      "WindSpeed": 37
    },
    {
      "group": "OldTomMorris_5Sep",
      "time": "2025-09-05T18:00:00+00:00",
      "Temperature": 13.2,
      "WindDirection": 257.0,
      "WindSpeed": 29
    }
  ]
}